my_loginUser/__init__.py
my_loginUser/cli.py
my_loginUser/main.py
my_loginuser-0.1.0.dist-info/METADATA
my_loginuser-0.1.0.dist-info/WHEEL
my_loginuser-0.1.0.dist-info/entry_points.txt
my_loginuser-0.1.0.dist-info/top_level.txt
my_loginuser-0.1.0.dist-info/RECORD
